README.rst
setup.py
bin/csv2gspread
df2gspread/__init__.py
df2gspread/_version.py
df2gspread/df2gspread.py
df2gspread/gfiles.py
df2gspread/gspread2df.py
df2gspread/utils.py
df2gspread.egg-info/PKG-INFO
df2gspread.egg-info/SOURCES.txt
df2gspread.egg-info/dependency_links.txt
df2gspread.egg-info/not-zip-safe
df2gspread.egg-info/pbr.json
df2gspread.egg-info/requires.txt
df2gspread.egg-info/top_level.txt