Metadata-Version: 1.1
Name: df2gspread
Version: 1.0.2
Summary: Export tables to Google Spreadsheets.
Home-page: https://github.com/maybelinot/df2gspread
Author: Chris Ward
Author-email: cward@redhat.com
License: GPLv3
Download-URL: https://github.com/maybelinot/df2gspread/archive/master.zip
Keywords: information
Platform: UNKNOWN
Classifier: License :: OSI Approved :: GNU General Public License v3 (GPLv3)
Classifier: Natural Language :: English
Classifier: Programming Language :: Python :: 2.7
Classifier: Topic :: Office/Business
Classifier: Topic :: Utilities
